{
  "Mindful": "You are a mindful micro-entrepreneur who takes money matters seriously",
  "Ambitious": "You have a very strong desire to be successful, it would require lots of effort, but that's okay for you.",
  "Confident": "You are a believer of yourself, confidence is your key",
  "Resourceful": "You are a go getter.",
  "Far-sighted": "Your vision for long term plans will lead your way.",
  "Accountable": "You are reliable",
  "Adaptable": "You can face challenges, adopt & grow.",
  "Creative": "You are fond of trying new things.",
  "Smart": "You have a sharp personality.",
  "Resilient": "You are strong enough to deal with shocks to bounce back like a pro.",
  "Lucid": "You are clear witted",
  "Will Power": "You have inner strength to withstand  challenges",
  "Learner": "An intelligent & adaptive personality like you can thrive in everything",
  "Necessity-driven": "Family is everything to you.",
  "Intuitive": "You believe in yourself, that’s the best thing about you",
  "Practical": "You are mostly rational",
  "Balanced": "You want to lead a simple yet enriching life",
  "Carefree": "You go by what you see and make decisions for today",
  "Conservative": "You are cautious  and calculative",
  "Determined": "Your perseverance can take you places"
}
